LICENSE
MANIFEST.in
README.md
setup.py
hihunter/__init__.py
hihunter/run.py
hihunter/version.py
hihunter.egg-info/PKG-INFO
hihunter.egg-info/SOURCES.txt
hihunter.egg-info/dependency_links.txt
hihunter.egg-info/entry_points.txt
hihunter.egg-info/requires.txt
hihunter.egg-info/top_level.txt
hihunter/cli/__init__.py
hihunter/cli/cli_hihunter_virustotal.py
hihunter/common/__init__.py
hihunter/common/common.py
hihunter/common/json2tree.py
hihunter/common/sqlite_db.py
hihunter/malwarebazaar/__init__.py
hihunter/malwarebazaar/malwarebazaar.py
hihunter/reddripsandbox/__init__.py
hihunter/reddripsandbox/reddripsandbox.py
hihunter/virustotal/__init__.py
hihunter/virustotal/virustotal.py