Metadata-Version: 2.1
Name: hihunter
Version: 1.0.6
Summary: 基于Virustotal的样本筛选工具
Home-page: https://github.com/a232319779/hihunter
Author: ddvv
Author-email: dadavivi512@gmail.com
License: MIT
Platform: UNKNOWN
Classifier: Programming Language :: Python :: 3
Classifier: License :: OSI Approved :: MIT License
Classifier: Operating System :: OS Independent
Requires-Python: >=3.6
License-File: LICENSE
